{
  "WorkflowsServiceV2Beta": {
    "methods": [
      {
        "type": "function",
        "function": {
          "name": "run_pipeline",
          "description": "Runs a pipeline. The returned Operation's [metadata]\n[google.longrunning.Operation.metadata] field will contain a\n[google.cloud.lifesciences.v2beta.Metadata][google.cloud.lifesciences.v2beta.Metadata]\nobject describing the status of the pipeline execution. The\n[response][google.longrunning.Operation.response] field will\ncontain a\n[google.cloud.lifesciences.v2beta.RunPipelineResponse][google.cloud.lifesciences.v2beta.RunPipelineResponse]\nobject if the pipeline completes successfully.\n\n**Note:** Before you can use this method, the *Life Sciences\nService Agent* must have access to your project. This is done\nautomatically when the Cloud Life Sciences API is first enabled,\nbut if you delete this permission you must disable and re-enable\nthe API to grant the Life Sciences Service Agent the required\npermissions. Authorization requires the following `Google\nIAM <https://cloud.google.com/iam/>`__ permission:\n\n-  ``lifesciences.workflows.run``\n\n.. code-block:: python\n\n    # This snippet has been automatically generated",
          "parameters": {
            "type": "object",
            "properties": {
              "request": {
                "type": "string",
                "description": ""
              },
              "retry": {
                "type": "string",
                "description": ""
              },
              "timeout": {
                "type": "string",
                "description": ""
              },
              "metadata": {
                "type": "string",
                "description": ""
              }
            },
            "required": [
              "request",
              "retry",
              "timeout",
              "metadata"
            ]
          },
          "request_types": [
            "workflows.RunPipelineRequest"
          ]
        }
      }
    ]
  }
}