{
  "\\Users\\AMD\\vidhra\\internal\\ast\\google-cloud-python\\packages\\google-cloud-assured-workloads\\google\\cloud\\assuredworkloads_v1\\types\\assuredworkloads.py": [
    {
      "type": "function",
      "name": "CreateWorkloadRequest",
      "description": "Request for creating a workload.\n\nAttributes:\n    parent (str):\n        Required. The resource name of the new Workload's parent.\n        Must be of the form\n        ``organizations/{org_id}/locations/{location_id}``.\n    workload (google.cloud.assuredworkloads_v1.types.Workload):\n        Required. Assured Workload to create\n    external_id (str):\n        Optional. A identifier associated with the\n        workload and underlying projects which allows\n        for the break down of billing costs for a\n        workload. The value provided for the identifier\n        will add a label to the workload and contained\n        projects with the identifier as the value.",
      "parameters": {
        "type": "object",
        "properties": {
          "parent": {
            "description": "Required. The resource name of the new Workload's parent. Must be of the form ``organizations/{org_id}/locations/{location_id}``.",
            "type": "string"
          },
          "workload": {
            "description": "Required. Assured Workload to create",
            "type": "object",
            "properties": {
              "name": {
                "description": "Identifier. Format: ``organizations/{organization}/locations/{location}/customers/{customer}/workloads/{workload}``",
                "type": "string"
              },
              "folder_id": {
                "description": "Output only. Folder id this workload is associated with",
                "type": "integer"
              },
              "create_time": {
                "description": "Output only. Time the resource was created.",
                "type": "object",
                "reference": "google.protobuf.timestamp_pb2.Timestamp"
              },
              "folder": {
                "description": "Output only. The name of container folder of the assured workload",
                "type": "string"
              },
              "workload_onboarding_state": {
                "type": "object",
                "properties": {
                  "onboarding_steps": {
                    "description": "List of workload onboarding steps.",
                    "type": "array",
                    "items": {
                      "type": "object",
                      "properties": {
                        "step": {
                          "type": "object",
                          "properties": {
                            "routine": {
                              "description": "Name of a routine within the workflow.",
                              "type": "string"
                            },
                            "step": {
                              "description": "Name of a step within the routine.",
                              "type": "string"
                            }
                          }
                        },
                        "start_time": {
                          "description": "The starting time of the onboarding step.",
                          "type": "object",
                          "reference": "google.protobuf.timestamp_pb2.Timestamp"
                        },
                        "completion_time": {
                          "description": "The completion time of the onboarding step.",
                          "type": "object",
                          "reference": "google.protobuf.timestamp_pb2.Timestamp"
                        },
                        "completion_state": {
                          "type": "enum",
                          "name": "CompletionState",
                          "description": "Enum for possible completion states.\n\nValues:\n    COMPLETION_STATE_UNSPECIFIED (0):\n        Unspecified completion state.\n    PENDING (1):\n        Task started (has start date) but not yet\n        completed.\n    SUCCEEDED (2):\n        Succeeded state.\n    FAILED (3):\n        Failed state.\n    NOT_APPLICABLE (4):\n        Not applicable state.",
                          "values": {
                            "COMPLETION_STATE_UNSPECIFIED": {
                              "value": 0
                            },
                            "PENDING": {
                              "value": 1
                            },
                            "SUCCEEDED": {
                              "value": 2
                            },
                            "FAILED": {
                              "value": 3
                            },
                            "NOT_APPLICABLE": {
                              "value": 4
                            }
                          }
                        }
                      }
                    }
                  }
                }
              },
              "is_onboarded": {
                "description": "Indicates whether a workload is fully onboarded.",
                "type": "boolean"
              },
              "key_management_project_id": {
                "description": "The project id of the key management project for the workload",
                "type": "string"
              },
              "location": {
                "description": "The Google Cloud location of the workload",
                "type": "string"
              },
              "partner": {
                "type": "object",
                "properties": {
                  "name": {
                    "description": "Identifier. The resource name of the partner. Format: ``organizations/{organization}/locations/{location}/partner`` Example: \"organizations/123456/locations/us-central1/partner\".",
                    "type": "string"
                  },
                  "skus": {
                    "description": "List of SKUs the partner is offering",
                    "type": "array",
                    "items": {
                      "type": "object",
                      "properties": {
                        "name": {
                          "description": "Identifier. Name of this SKU. Format: ``projects/{project}/locations/{location}/skus/{sku}``",
                          "type": "string"
                        },
                        "display_name": {
                          "description": "Output only. Display name of this SKU.",
                          "type": "string"
                        },
                        "create_time": {
                          "description": "Output only. Time when this SKU was created.",
                          "type": "object",
                          "reference": "google.protobuf.timestamp_pb2.Timestamp"
                        },
                        "update_time": {
                          "description": "Output only. Time when this SKU was last updated.",
                          "type": "object",
                          "reference": "google.protobuf.timestamp_pb2.Timestamp"
                        },
                        "config": {
                          "type": "object",
                          "properties": {
                            "cpu": {
                              "description": "Information about CPU configuration.",
                              "type": "string"
                            },
                            "gpu": {
                              "description": "Information about GPU configuration.",
                              "type": "string"
                            },
                            "ram": {
                              "description": "Information about RAM configuration.",
                              "type": "string"
                            },
                            "storage": {
                              "description": "Information about storage configuration.",
                              "type": "string"
                            }
                          }
                        },
                        "instances": {
                          "description": "Output only. Available instances of this SKU. This field should be used for checking availability of a SKU.",
                          "type": "array",
                          "items": {
                            "type": "object",
                            "properties": {
                              "region_code": {
                                "description": "The `Unicode CLDR <https://cldr.unicode.org>`__ region code where this instance is available.",
                                "type": "string"
                              },
                              "power_supply": {
                                "type": "enum",
                                "name": "PowerSupply",
                                "description": "The power supply options.\n\nValues:\n    POWER_SUPPLY_UNSPECIFIED (0):\n        Power supply is unspecified.\n    POWER_SUPPLY_AC (1):\n        AC power supply.\n    POWER_SUPPLY_DC (2):\n        DC power supply.",
                                "values": {
                                  "POWER_SUPPLY_UNSPECIFIED": {
                                    "value": 0
                                  },
                                  "POWER_SUPPLY_AC": {
                                    "value": 1
                                  },
                                  "POWER_SUPPLY_DC": {
                                    "value": 2
                                  }
                                }
                              },
                              "billing_sku": {
                                "description": "Reference to the corresponding SKU in the Cloud Billing API. The estimated price information can be retrieved using that API. Format: ``services/{service}/skus/{sku}``",
                                "type": "string"
                              },
                              "billing_sku_per_vcpu": {
                                "description": "Reference to the corresponding SKU per vCPU in the Cloud Billing API. The estimated price information can be retrieved using that API. Format: ``services/{service}/skus/{sku}``",
                                "type": "string"
                              },
                              "subscription_duration_months": {
                                "description": "Subscription duration for the hardware in months.",
                                "type": "integer"
                              }
                            }
                          }
                        },
                        "description": {
                          "description": "Output only. Description of this SKU.",
                          "type": "string"
                        },
                        "revision_id": {
                          "description": "Output only. The SKU revision ID. A new revision is created whenever ``config`` is updated. The format is an 8-character hexadecimal string.",
                          "type": "string"
                        },
                        "is_active": {
                          "description": "Output only. Flag to indicate whether or not this revision is active. Only an active revision can be used in a new Order.",
                          "type": "boolean"
                        },
                        "type_": {
                          "type": "enum",
                          "name": "Type",
                          "description": "Return policy types.\n\nValues:\n    TYPE_UNSPECIFIED (0):\n        Default value. This value is unused.\n    NUMBER_OF_DAYS_AFTER_DELIVERY (1):\n        The number of days within which a return is\n        valid after delivery.\n    NO_RETURNS (2):\n        No returns.\n    LIFETIME_RETURNS (3):\n        Life time returns.",
                          "values": {
                            "TYPE_UNSPECIFIED": {
                              "value": 0
                            },
                            "NUMBER_OF_DAYS_AFTER_DELIVERY": {
                              "value": 1
                            },
                            "NO_RETURNS": {
                              "value": 2
                            },
                            "LIFETIME_RETURNS": {
                              "value": 3
                            }
                          }
                        },
                        "vcpu_count": {
                          "description": "Output only. The vCPU count associated with this SKU.",
                          "type": "integer"
                        }
                      }
                    }
                  },
                  "ekm_solutions": {
                    "description": "List of Google Cloud supported EKM partners supported by the partner",
                    "type": "array",
                    "items": {
                      "type": "object",
                      "properties": {
                        "ekm_solution": {
                          "type": "enum",
                          "name": "EkmSolution",
                          "description": "Represents Google Cloud supported external key management partners\n`Google Cloud EKM partners\ndocs <https://cloud.google.com/kms/docs/ekm#supported_partners>`__.\n\nValues:\n    EKM_SOLUTION_UNSPECIFIED (0):\n        Unspecified EKM solution\n    FORTANIX (1):\n        EKM Partner Fortanix\n    FUTUREX (2):\n        EKM Partner FutureX\n    THALES (3):\n        EKM Partner Thales\n    VIRTRU (4):\n        EKM Partner Virtu",
                          "values": {
                            "EKM_SOLUTION_UNSPECIFIED": {
                              "value": 0
                            },
                            "FORTANIX": {
                              "value": 1
                            },
                            "FUTUREX": {
                              "value": 2
                            },
                            "THALES": {
                              "value": 3
                            },
                            "VIRTRU": {
                              "value": 4
                            }
                          }
                        },
                        "ekm_endpoint_uri": {
                          "description": "Endpoint for sending requests to the EKM for key provisioning during Assured Workload creation.",
                          "type": "string"
                        }
                      }
                    }
                  },
                  "operated_cloud_regions": {
                    "description": "List of Google Cloud regions that the partner sells services to customers. Valid Google Cloud regions found here:  https://cloud.google.com/compute/docs/regions-zones",
                    "type": "array",
                    "items": {
                      "type": "string"
                    }
                  },
                  "partner_project_id": {
                    "description": "Google Cloud project ID in the partner's Google Cloud organization for receiving enhanced Logs for Partners.",
                    "type": "string"
                  },
                  "create_time": {
                    "description": "Output only. Time the resource was created",
                    "type": "object",
                    "reference": "google.protobuf.timestamp_pb2.Timestamp"
                  },
                  "update_time": {
                    "description": "Output only. The last time the resource was updated",
                    "type": "object",
                    "reference": "google.protobuf.timestamp_pb2.Timestamp"
                  }
                }
              }
            }
          },
          "external_id": {
            "description": "Optional. A identifier associated with the workload and underlying projects which allows for the break down of billing costs for a workload. The value provided for the identifier will add a label to the workload and contained projects with the identifier as the value.",
            "type": "string"
          }
        },
        "required": [
          "parent",
          "workload"
        ]
      }
    },
    {
      "type": "function",
      "name": "UpdateWorkloadRequest",
      "description": "Request for Updating a workload.\n\nAttributes:\n    workload (google.cloud.assuredworkloads_v1.types.Workload):\n        Required. The workload to update. The workload's ``name``\n        field is used to identify the workload to be updated.\n        Format:\n        organizations/{org_id}/locations/{location_id}/workloads/{workload_id}\n    update_mask (google.protobuf.field_mask_pb2.FieldMask):\n        Required. The list of fields to be updated.",
      "parameters": {
        "type": "object",
        "properties": {
          "workload": {
            "description": "Required. The workload to update. The workload's ``name`` field is used to identify the workload to be updated. Format: organizations/{org_id}/locations/{location_id}/workloads/{workload_id}",
            "type": "object",
            "properties": {
              "name": {
                "description": "Identifier. Format: ``organizations/{organization}/locations/{location}/customers/{customer}/workloads/{workload}``",
                "type": "string"
              },
              "folder_id": {
                "description": "Output only. Folder id this workload is associated with",
                "type": "integer"
              },
              "create_time": {
                "description": "Output only. Time the resource was created.",
                "type": "object",
                "reference": "google.protobuf.timestamp_pb2.Timestamp"
              },
              "folder": {
                "description": "Output only. The name of container folder of the assured workload",
                "type": "string"
              },
              "workload_onboarding_state": {
                "type": "object",
                "properties": {
                  "onboarding_steps": {
                    "description": "List of workload onboarding steps.",
                    "type": "array",
                    "items": {
                      "type": "object",
                      "properties": {
                        "step": {
                          "type": "object",
                          "properties": {
                            "routine": {
                              "description": "Name of a routine within the workflow.",
                              "type": "string"
                            },
                            "step": {
                              "description": "Name of a step within the routine.",
                              "type": "string"
                            }
                          }
                        },
                        "start_time": {
                          "description": "The starting time of the onboarding step.",
                          "type": "object",
                          "reference": "google.protobuf.timestamp_pb2.Timestamp"
                        },
                        "completion_time": {
                          "description": "The completion time of the onboarding step.",
                          "type": "object",
                          "reference": "google.protobuf.timestamp_pb2.Timestamp"
                        },
                        "completion_state": {
                          "type": "enum",
                          "name": "CompletionState",
                          "description": "Enum for possible completion states.\n\nValues:\n    COMPLETION_STATE_UNSPECIFIED (0):\n        Unspecified completion state.\n    PENDING (1):\n        Task started (has start date) but not yet\n        completed.\n    SUCCEEDED (2):\n        Succeeded state.\n    FAILED (3):\n        Failed state.\n    NOT_APPLICABLE (4):\n        Not applicable state.",
                          "values": {
                            "COMPLETION_STATE_UNSPECIFIED": {
                              "value": 0
                            },
                            "PENDING": {
                              "value": 1
                            },
                            "SUCCEEDED": {
                              "value": 2
                            },
                            "FAILED": {
                              "value": 3
                            },
                            "NOT_APPLICABLE": {
                              "value": 4
                            }
                          }
                        }
                      }
                    }
                  }
                }
              },
              "is_onboarded": {
                "description": "Indicates whether a workload is fully onboarded.",
                "type": "boolean"
              },
              "key_management_project_id": {
                "description": "The project id of the key management project for the workload",
                "type": "string"
              },
              "location": {
                "description": "The Google Cloud location of the workload",
                "type": "string"
              },
              "partner": {
                "type": "object",
                "properties": {
                  "name": {
                    "description": "Identifier. The resource name of the partner. Format: ``organizations/{organization}/locations/{location}/partner`` Example: \"organizations/123456/locations/us-central1/partner\".",
                    "type": "string"
                  },
                  "skus": {
                    "description": "List of SKUs the partner is offering",
                    "type": "array",
                    "items": {
                      "type": "object",
                      "properties": {
                        "name": {
                          "description": "Identifier. Name of this SKU. Format: ``projects/{project}/locations/{location}/skus/{sku}``",
                          "type": "string"
                        },
                        "display_name": {
                          "description": "Output only. Display name of this SKU.",
                          "type": "string"
                        },
                        "create_time": {
                          "description": "Output only. Time when this SKU was created.",
                          "type": "object",
                          "reference": "google.protobuf.timestamp_pb2.Timestamp"
                        },
                        "update_time": {
                          "description": "Output only. Time when this SKU was last updated.",
                          "type": "object",
                          "reference": "google.protobuf.timestamp_pb2.Timestamp"
                        },
                        "config": {
                          "type": "object",
                          "properties": {
                            "cpu": {
                              "description": "Information about CPU configuration.",
                              "type": "string"
                            },
                            "gpu": {
                              "description": "Information about GPU configuration.",
                              "type": "string"
                            },
                            "ram": {
                              "description": "Information about RAM configuration.",
                              "type": "string"
                            },
                            "storage": {
                              "description": "Information about storage configuration.",
                              "type": "string"
                            }
                          }
                        },
                        "instances": {
                          "description": "Output only. Available instances of this SKU. This field should be used for checking availability of a SKU.",
                          "type": "array",
                          "items": {
                            "type": "object",
                            "properties": {
                              "region_code": {
                                "description": "The `Unicode CLDR <https://cldr.unicode.org>`__ region code where this instance is available.",
                                "type": "string"
                              },
                              "power_supply": {
                                "type": "enum",
                                "name": "PowerSupply",
                                "description": "The power supply options.\n\nValues:\n    POWER_SUPPLY_UNSPECIFIED (0):\n        Power supply is unspecified.\n    POWER_SUPPLY_AC (1):\n        AC power supply.\n    POWER_SUPPLY_DC (2):\n        DC power supply.",
                                "values": {
                                  "POWER_SUPPLY_UNSPECIFIED": {
                                    "value": 0
                                  },
                                  "POWER_SUPPLY_AC": {
                                    "value": 1
                                  },
                                  "POWER_SUPPLY_DC": {
                                    "value": 2
                                  }
                                }
                              },
                              "billing_sku": {
                                "description": "Reference to the corresponding SKU in the Cloud Billing API. The estimated price information can be retrieved using that API. Format: ``services/{service}/skus/{sku}``",
                                "type": "string"
                              },
                              "billing_sku_per_vcpu": {
                                "description": "Reference to the corresponding SKU per vCPU in the Cloud Billing API. The estimated price information can be retrieved using that API. Format: ``services/{service}/skus/{sku}``",
                                "type": "string"
                              },
                              "subscription_duration_months": {
                                "description": "Subscription duration for the hardware in months.",
                                "type": "integer"
                              }
                            }
                          }
                        },
                        "description": {
                          "description": "Output only. Description of this SKU.",
                          "type": "string"
                        },
                        "revision_id": {
                          "description": "Output only. The SKU revision ID. A new revision is created whenever ``config`` is updated. The format is an 8-character hexadecimal string.",
                          "type": "string"
                        },
                        "is_active": {
                          "description": "Output only. Flag to indicate whether or not this revision is active. Only an active revision can be used in a new Order.",
                          "type": "boolean"
                        },
                        "type_": {
                          "type": "enum",
                          "name": "Type",
                          "description": "Return policy types.\n\nValues:\n    TYPE_UNSPECIFIED (0):\n        Default value. This value is unused.\n    NUMBER_OF_DAYS_AFTER_DELIVERY (1):\n        The number of days within which a return is\n        valid after delivery.\n    NO_RETURNS (2):\n        No returns.\n    LIFETIME_RETURNS (3):\n        Life time returns.",
                          "values": {
                            "TYPE_UNSPECIFIED": {
                              "value": 0
                            },
                            "NUMBER_OF_DAYS_AFTER_DELIVERY": {
                              "value": 1
                            },
                            "NO_RETURNS": {
                              "value": 2
                            },
                            "LIFETIME_RETURNS": {
                              "value": 3
                            }
                          }
                        },
                        "vcpu_count": {
                          "description": "Output only. The vCPU count associated with this SKU.",
                          "type": "integer"
                        }
                      }
                    }
                  },
                  "ekm_solutions": {
                    "description": "List of Google Cloud supported EKM partners supported by the partner",
                    "type": "array",
                    "items": {
                      "type": "object",
                      "properties": {
                        "ekm_solution": {
                          "type": "enum",
                          "name": "EkmSolution",
                          "description": "Represents Google Cloud supported external key management partners\n`Google Cloud EKM partners\ndocs <https://cloud.google.com/kms/docs/ekm#supported_partners>`__.\n\nValues:\n    EKM_SOLUTION_UNSPECIFIED (0):\n        Unspecified EKM solution\n    FORTANIX (1):\n        EKM Partner Fortanix\n    FUTUREX (2):\n        EKM Partner FutureX\n    THALES (3):\n        EKM Partner Thales\n    VIRTRU (4):\n        EKM Partner Virtu",
                          "values": {
                            "EKM_SOLUTION_UNSPECIFIED": {
                              "value": 0
                            },
                            "FORTANIX": {
                              "value": 1
                            },
                            "FUTUREX": {
                              "value": 2
                            },
                            "THALES": {
                              "value": 3
                            },
                            "VIRTRU": {
                              "value": 4
                            }
                          }
                        },
                        "ekm_endpoint_uri": {
                          "description": "Endpoint for sending requests to the EKM for key provisioning during Assured Workload creation.",
                          "type": "string"
                        }
                      }
                    }
                  },
                  "operated_cloud_regions": {
                    "description": "List of Google Cloud regions that the partner sells services to customers. Valid Google Cloud regions found here:  https://cloud.google.com/compute/docs/regions-zones",
                    "type": "array",
                    "items": {
                      "type": "string"
                    }
                  },
                  "partner_project_id": {
                    "description": "Google Cloud project ID in the partner's Google Cloud organization for receiving enhanced Logs for Partners.",
                    "type": "string"
                  },
                  "create_time": {
                    "description": "Output only. Time the resource was created",
                    "type": "object",
                    "reference": "google.protobuf.timestamp_pb2.Timestamp"
                  },
                  "update_time": {
                    "description": "Output only. The last time the resource was updated",
                    "type": "object",
                    "reference": "google.protobuf.timestamp_pb2.Timestamp"
                  }
                }
              }
            }
          },
          "update_mask": {
            "description": "Required. The list of fields to be updated.",
            "type": "object",
            "reference": "google.protobuf.field_mask_pb2.FieldMask"
          }
        },
        "required": [
          "workload",
          "update_mask"
        ]
      }
    },
    {
      "type": "function",
      "name": "DeleteWorkloadRequest",
      "description": "Request for deleting a Workload.\n\nAttributes:\n    name (str):\n        Required. The ``name`` field is used to identify the\n        workload. Format:\n        organizations/{org_id}/locations/{location_id}/workloads/{workload_id}\n    etag (str):\n        Optional. The etag of the workload.\n        If this is provided, it must match the server's\n        etag.",
      "parameters": {
        "type": "object",
        "properties": {
          "name": {
            "description": "Required. The ``name`` field is used to identify the workload. Format: organizations/{org_id}/locations/{location_id}/workloads/{workload_id}",
            "type": "string"
          },
          "etag": {
            "description": "Optional. The etag of the workload. If this is provided, it must match the server's etag.",
            "type": "string"
          }
        },
        "required": [
          "name"
        ]
      }
    },
    {
      "type": "function",
      "name": "GetWorkloadRequest",
      "description": "Request for fetching a workload.\n\nAttributes:\n    name (str):\n        Required. The resource name of the Workload to fetch. This\n        is the workload's relative path in the API, formatted as\n        \"organizations/{organization_id}/locations/{location_id}/workloads/{workload_id}\".\n        For example,\n        \"organizations/123/locations/us-east1/workloads/assured-workload-1\".",
      "parameters": {
        "type": "object",
        "properties": {
          "name": {
            "description": "Required. The resource name of the Workload to fetch. This is the workload's relative path in the API, formatted as \"organizations/{organization_id}/locations/{location_id}/workloads/{workload_id}\". For example, \"organizations/123/locations/us-east1/workloads/assured-workload-1\".",
            "type": "string"
          }
        },
        "required": [
          "name"
        ]
      }
    },
    {
      "type": "function",
      "name": "ListWorkloadsRequest",
      "description": "Request for fetching workloads in an organization.\n\nAttributes:\n    parent (str):\n        Required. Parent Resource to list workloads from. Must be of\n        the form ``organizations/{org_id}/locations/{location}``.\n    page_size (int):\n        Page size.\n    page_token (str):\n        Page token returned from previous request.\n        Page token contains context from previous\n        request. Page token needs to be passed in the\n        second and following requests.\n    filter (str):\n        A custom filter for filtering by properties\n        of a workload. At this time, only filtering by\n        labels is supported.",
      "parameters": {
        "type": "object",
        "properties": {
          "parent": {
            "description": "Required. Parent Resource to list workloads from. Must be of the form ``organizations/{org_id}/locations/{location}``.",
            "type": "string"
          },
          "page_size": {
            "description": "Page size.",
            "type": "integer"
          },
          "page_token": {
            "description": "Page token returned from previous request. Page token contains context from previous request. Page token needs to be passed in the second and following requests.",
            "type": "string"
          },
          "filter": {
            "description": "A custom filter for filtering by properties of a workload. At this time, only filtering by labels is supported.",
            "type": "string"
          }
        },
        "required": [
          "parent"
        ]
      }
    },
    {
      "type": "function",
      "name": "RestrictAllowedResourcesRequest",
      "description": "Request for restricting list of available resources in\nWorkload environment.\n\nAttributes:\n    name (str):\n        Required. The resource name of the Workload. This is the\n        workloads's relative path in the API, formatted as\n        \"organizations/{organization_id}/locations/{location_id}/workloads/{workload_id}\".\n        For example,\n        \"organizations/123/locations/us-east1/workloads/assured-workload-1\".\n    restriction_type (google.cloud.assuredworkloads_v1.types.RestrictAllowedResourcesRequest.RestrictionType):\n        Required. The type of restriction for using\n        gcp products in the Workload environment.",
      "parameters": {
        "type": "object",
        "properties": {
          "name": {
            "description": "Required. The resource name of the Workload. This is the workloads's relative path in the API, formatted as \"organizations/{organization_id}/locations/{location_id}/workloads/{workload_id}\". For example, \"organizations/123/locations/us-east1/workloads/assured-workload-1\".",
            "type": "string"
          },
          "restriction_type": {
            "description": "The type of restriction.\n\nValues:\n    RESTRICTION_TYPE_UNSPECIFIED (0):\n        Unknown restriction type.\n    ALLOW_ALL_GCP_RESOURCES (1):\n        Allow the use all of all gcp products,\n        irrespective of the compliance posture. This\n        effectively removes gcp.restrictServiceUsage\n        OrgPolicy on the AssuredWorkloads Folder.\n    ALLOW_COMPLIANT_RESOURCES (2):\n        Based on Workload's compliance regime,\n        allowed list changes. See -\n        https://cloud.google.com/assured-workloads/docs/supported-products\n        for the list of supported resources.",
            "type": "enum",
            "name": "RestrictionType",
            "values": {
              "RESTRICTION_TYPE_UNSPECIFIED": {
                "value": 0
              },
              "ALLOW_ALL_GCP_RESOURCES": {
                "value": 1
              },
              "ALLOW_COMPLIANT_RESOURCES": {
                "value": 2
              }
            }
          }
        },
        "required": [
          "name",
          "restriction_type"
        ]
      }
    },
    {
      "type": "function",
      "name": "AcknowledgeViolationRequest",
      "description": "Request for acknowledging the violation\nNext Id: 4\n\nAttributes:\n    name (str):\n        Required. The resource name of the Violation\n        to acknowledge. Format:\n\n        organizations/{organization}/locations/{location}/workloads/{workload}/violations/{violation}\n    comment (str):\n        Required. Business justification explaining\n        the need for violation acknowledgement\n    non_compliant_org_policy (str):\n        Optional. This field is deprecated and will be removed in\n        future version of the API. Name of the OrgPolicy which was\n        modified with non-compliant change and resulted in this\n        violation. Format:\n        projects/{project_number}/policies/{constraint_name}\n        folders/{folder_id}/policies/{constraint_name}\n        organizations/{organization_id}/policies/{constraint_name}",
      "parameters": {
        "type": "object",
        "properties": {
          "name": {
            "description": "Required. The resource name of the Violation to acknowledge. Format:  organizations/{organization}/locations/{location}/workloads/{workload}/violations/{violation}",
            "type": "string"
          },
          "comment": {
            "description": "Required. Business justification explaining the need for violation acknowledgement",
            "type": "string"
          },
          "non_compliant_org_policy": {
            "description": "Optional. This field is deprecated and will be removed in future version of the API. Name of the OrgPolicy which was modified with non-compliant change and resulted in this violation. Format: projects/{project_number}/policies/{constraint_name} folders/{folder_id}/policies/{constraint_name} organizations/{organization_id}/policies/{constraint_name}",
            "type": "string"
          }
        },
        "required": [
          "name",
          "comment"
        ]
      }
    },
    {
      "type": "function",
      "name": "ListViolationsRequest",
      "description": "Request for fetching violations in an organization.\n\nAttributes:\n    parent (str):\n        Required. The Workload name. Format\n        ``organizations/{org_id}/locations/{location}/workloads/{workload}``.\n    interval (google.cloud.assuredworkloads_v1.types.TimeWindow):\n        Optional. Specifies the time window for retrieving active\n        Violations. When specified, retrieves Violations that were\n        active between start_time and end_time.\n    page_size (int):\n        Optional. Page size.\n    page_token (str):\n        Optional. Page token returned from previous\n        request.\n    filter (str):\n        Optional. A custom filter for filtering by\n        the Violations properties.",
      "parameters": {
        "type": "object",
        "properties": {
          "parent": {
            "description": "Required. The Workload name. Format ``organizations/{org_id}/locations/{location}/workloads/{workload}``.",
            "type": "string"
          },
          "interval": {
            "description": "Optional. Specifies the time window for retrieving active Violations. When specified, retrieves Violations that were active between start_time and end_time.",
            "type": "object",
            "properties": {
              "start_time": {
                "description": "The hard time window start time. If unspecified it will be set to ``ShipmentModel.global_start_time``.",
                "type": "object",
                "reference": "google.protobuf.timestamp_pb2.Timestamp"
              },
              "end_time": {
                "description": "The hard time window end time. If unspecified it will be set to ``ShipmentModel.global_end_time``.",
                "type": "object",
                "reference": "google.protobuf.timestamp_pb2.Timestamp"
              },
              "soft_start_time": {
                "description": "The soft start time of the time window.",
                "type": "object",
                "reference": "google.protobuf.timestamp_pb2.Timestamp"
              },
              "soft_end_time": {
                "description": "The soft end time of the time window.",
                "type": "object",
                "reference": "google.protobuf.timestamp_pb2.Timestamp"
              },
              "cost_per_hour_before_soft_start_time": {
                "description": "A cost per hour added to other costs in the model if the event occurs before soft_start_time, computed as:  ::  max(0, soft_start_time - t.seconds) * cost_per_hour_before_soft_start_time / 3600, t being the time of the event.  This cost must be positive, and the field can only be set if soft_start_time has been set.  This field is a member of `oneof`_ ``_cost_per_hour_before_soft_start_time``.",
                "type": "number"
              },
              "cost_per_hour_after_soft_end_time": {
                "description": "A cost per hour added to other costs in the model if the event occurs after ``soft_end_time``, computed as:  ::  max(0, t.seconds - soft_end_time.seconds) * cost_per_hour_after_soft_end_time / 3600, t being the time of the event.  This cost must be positive, and the field can only be set if ``soft_end_time`` has been set.  This field is a member of `oneof`_ ``_cost_per_hour_after_soft_end_time``.",
                "type": "number"
              }
            }
          },
          "page_size": {
            "description": "Optional. Page size.",
            "type": "integer"
          },
          "page_token": {
            "description": "Optional. Page token returned from previous request.",
            "type": "string"
          },
          "filter": {
            "description": "Optional. A custom filter for filtering by the Violations properties.",
            "type": "string"
          }
        },
        "required": [
          "parent"
        ]
      }
    },
    {
      "type": "function",
      "name": "GetViolationRequest",
      "description": "Request for fetching a Workload Violation.\n\nAttributes:\n    name (str):\n        Required. The resource name of the Violation\n        to fetch (ie. Violation.name). Format:\n\n        organizations/{organization}/locations/{location}/workloads/{workload}/violations/{violation}",
      "parameters": {
        "type": "object",
        "properties": {
          "name": {
            "description": "Required. The resource name of the Violation to fetch (ie. Violation.name). Format:  organizations/{organization}/locations/{location}/workloads/{workload}/violations/{violation}",
            "type": "string"
          }
        },
        "required": [
          "name"
        ]
      }
    }
  ]
}